{
    "Quinta": {
        "almoco": {
            "proteina": "FRICASSÉ DE FRANGO",
            "carboidrato": "ARROZ E FEIJÃO",
            "guarnicao": "ARROZ COLORIDO (CENOURA, ERVILHA, MILHO E SALSA)",
            "salada": "SALADA DE PEPINO",
            "sobremesa": {
                "RU": "GOIABADA",
                "RA": "GOIABADA",
                "HC": "GOIABADA",
                "RS": "GOIABADA"
            },
            "suco": "REFRESCO DE LARANJA"
        },
        "jantar": {
            "proteina": "ALMÔNDEGA AO POMODORO",
            "carboidrato": "ARROZ E FEIJÃO",
            "guarnicao": "BATATA À PORTUGUESA (CEBOLA, PIMENTÃO, AZEITONA E TOMATE)",
            "salada": "SALADA DE CENOURA RALADA",
            "sobremesa": {
                "RU": "MELANCIA",
                "RA": "MELANCIA",
                "HC": "MELANCIA",
                "RS": "MELANCIA"
            },
            "suco": "REFRESCO DE LARANJA"
        }
    },
    "Sexta": {
        "almoco": {
            "proteina": "QUIBE ASSADO",
            "carboidrato": "ARROZ E FEIJÃO",
            "guarnicao": "ABOBRINHA REFOGADA",
            "salada": "SALADA DE REPOLHO BICOLOR",
            "sobremesa": {
                "RU": "LARANJA",
                "RA": "LARANJA",
                "HC": "LARANJA",
                "RS": "LARANJA"
            },
            "suco": "REFRESCO DE GOIABA"
        },
        "jantar": {
            "proteina": "FILEZINHO DE FRANGO ACEBOLADO",
            "carboidrato": "ARROZ E FEIJÃO",
            "guarnicao": "QUIBEBE",
            "salada": "SALADA DE ESCAROLA",
            "sobremesa": {
                "RU": "GOIABADA",
                "RA": "GOIABADA",
                "HC": "GOIABADA",
                "RS": "GOIABADA"
            },
            "suco": "REFRESCO DE GOIABA"
        }
    },
    "Sábado": {
        "almoco": {
            "proteina": "ISCA DE FRANGO AO MOLHO DE BACON",
            "carboidrato": "ARROZ E FEIJÃO",
            "guarnicao": "BATATA PALHA",
            "salada": "SALADA DE ALMEIRÃO",
            "sobremesa": {
                "RU": "MAÇÃ",
                "RA": "MAÇÃ",
                "HC": "MAÇÃ",
                "RS": "MAÇÃ"
            },
            "suco": "REFRESCO DE UVA"
        },
        "jantar": {
            "proteina": "LINGUIÇA ASSADA",
            "carboidrato": "ARROZ E FEIJÃO",
            "guarnicao": "COUVE REFOGADA",
            "salada": "SALADA DE ALFACE",
            "sobremesa": {
                "RU": "MELÃO",
                "RA": "MELÃO",
                "HC": "MELÃO",
                "RS": "MELÃO"
            },
            "suco": "REFRESCO DE UVA"
        }
    },
    "Domingo": {
        "almoco": {
            "proteina": "BIFE DE PANELA AO MOLHO SUGO",
            "carboidrato": "ARROZ E FEIJÃO",
            "guarnicao": "REPOLHO REFOGADO",
            "salada": "SALADA DE BETERRABA RALADA",
            "sobremesa": {
                "RU": "MELANCIA",
                "RA": "MELANCIA",
                "HC": "MELANCIA",
                "RS": "MELANCIA"
            },
            "suco": "REFRESCO DE MANGA"
        }
    }
}